model_diagnostics/__about__.py
model_diagnostics/__init__.py
model_diagnostics/_config.py
model_diagnostics/_utils/__init__.py
model_diagnostics/_utils/array.py
model_diagnostics/_utils/binning.py
model_diagnostics/_utils/isotonic.py
model_diagnostics/_utils/partial_dependence.py
model_diagnostics/_utils/plot_helper.py
model_diagnostics/_utils/test_helper.py
model_diagnostics/_utils/tests/test_array.py
model_diagnostics/_utils/tests/test_binning.py
model_diagnostics/_utils/tests/test_isotonic.py
model_diagnostics/_utils/tests/test_partial_dependence.py
model_diagnostics/calibration/__init__.py
model_diagnostics/calibration/identification.py
model_diagnostics/calibration/plots.py
model_diagnostics/calibration/tests/__init__.py
model_diagnostics/calibration/tests/test_identification.py
model_diagnostics/calibration/tests/test_plots.py
model_diagnostics/scoring/__init__.py
model_diagnostics/scoring/plots.py
model_diagnostics/scoring/scoring.py
model_diagnostics/scoring/tests/__init__.py
model_diagnostics/scoring/tests/test_plots.py
model_diagnostics/scoring/tests/test_scoring.py
model_diagnostics/tests/test_config.py
model_diagnostics-1.4.3.dist-info/METADATA
model_diagnostics-1.4.3.dist-info/WHEEL
model_diagnostics-1.4.3.dist-info/licenses/LICENSE
model_diagnostics-1.4.3.dist-info/RECORD
