Metadata-Version: 2.4
Name: model-diagnostics
Version: 1.4.3
Summary: Tools for diagnostics and assessment of (machine learning) models
Project-URL: Homepage, https://lorentzenchr.github.io/model-diagnostics/
Project-URL: Source, https://github.com/lorentzenchr/model-diagnostics
Project-URL: Tracker, https://github.com/lorentzenchr/model-diagnostics/issues
Author-email: Christian Lorentzen <lorentzen.ch@gmail.com>
License: MIT License
License-File: LICENSE
Keywords: calibration,machine learning,model diagnostics
Classifier: Development Status :: 5 - Production/Stable
Classifier: Framework :: Hatch
Classifier: License :: OSI Approved :: MIT License
Classifier: Operating System :: OS Independent
Classifier: Programming Language :: Python :: 3
Classifier: Topic :: Scientific/Engineering
Requires-Python: >=3.11
Requires-Dist: matplotlib>=3.8.4
Requires-Dist: numpy>=2.0.0
Requires-Dist: packaging>=23.1
Requires-Dist: polars>=1.1.0
Requires-Dist: scikit-learn>=1.4.2
Requires-Dist: scipy>=1.13.1
